LICENSE.txt
README.md
setup.py
voussoirkit/__init__.py
voussoirkit/backoff.py
voussoirkit/basenumber.py
voussoirkit/bencode.py
voussoirkit/betterhelp.py
voussoirkit/bytestring.py
voussoirkit/cacheclass.py
voussoirkit/configlayers.py
voussoirkit/dotdict.py
voussoirkit/downloady.py
voussoirkit/eternalseptember.py
voussoirkit/expressionmatch.py
voussoirkit/flasktools.py
voussoirkit/fusker.py
voussoirkit/gentools.py
voussoirkit/hms.py
voussoirkit/httperrors.py
voussoirkit/imagetools.py
voussoirkit/interactive.py
voussoirkit/kbps.py
voussoirkit/lazychain.py
voussoirkit/mutables.py
voussoirkit/networktools.py
voussoirkit/niceprints.py
voussoirkit/operatornotify.py
voussoirkit/passwordy.py
voussoirkit/pathclass.py
voussoirkit/pipeable.py
voussoirkit/progressbars.py
voussoirkit/quickid.py
voussoirkit/ratelimiter.py
voussoirkit/ratemeter.py
voussoirkit/safeprint.py
voussoirkit/sentinel.py
voussoirkit/spinal.py
voussoirkit/sqlhelpers.py
voussoirkit/stringtools.py
voussoirkit/subproctools.py
voussoirkit/threadpool.py
voussoirkit/timetools.py
voussoirkit/treeclass.py
voussoirkit/vlogging.py
voussoirkit/windrives.py
voussoirkit/winglob.py
voussoirkit/winwhich.py
voussoirkit/worms.py
voussoirkit.egg-info/PKG-INFO
voussoirkit.egg-info/SOURCES.txt
voussoirkit.egg-info/dependency_links.txt
voussoirkit.egg-info/requires.txt
voussoirkit.egg-info/top_level.txt