Metadata-Version: 2.1
Name: voussoirkit
Version: 0.0.75
Summary: voussoir's toolkit
Home-page: https://github.com/voussoir/voussoirkit
Author: voussoir
Author-email: pypi@voussoir.net
License: UNKNOWN
Platform: UNKNOWN
